Metadata-Version: 1.1
Name: make-distributions-py
Version: 0.1
Summary: Gaussian distributions
Home-page: UNKNOWN
Author: Ridwan Salahuddeen
Author-email: ridzy619@yahoo.com
License: UNKNOWN
Platform: UNKNOWN
Classifier: Programming Language :: Python :: 3
Classifier: License :: OSI Approved :: MIT License
Classifier: Operating System :: OS Independent
